logging_extended_handlers/__init__.py
logging_extended_handlers/_version.py
logging_extended_handlers/http_handler.py
logging_extended_handlers/smtp_handler.py
logging_extended_handlers-0.2.1.dist-info/METADATA
logging_extended_handlers-0.2.1.dist-info/WHEEL
logging_extended_handlers-0.2.1.dist-info/licenses/LICENSE
logging_extended_handlers-0.2.1.dist-info/RECORD
