Metadata-Version: 2.4
Name: logging-extended-handlers
Version: 0.2.1
Summary: Extending logging.handlers
Project-URL: Changelog, https://github.com/m-birke/logging-extended-handlers/blob/main/CHANGELOG.md
Project-URL: Documentation, https://github.com/m-birke/logging-extended-handlers#readme
Project-URL: Homepage, https://github.com/m-birke/logging-extended-handlers
Project-URL: Issues, https://github.com/m-birke/logging-extended-handlers/issues
Project-URL: Source, https://github.com/m-birke/logging-extended-handlers
Author-email: m-birke <wesci@web.de>
License-Expression: MIT
License-File: LICENSE
Keywords: handlers,header,headers,http,log,log handlers,logging,logging handlers,mail,smtp
Classifier: Development Status :: 4 - Beta
Classifier: License :: OSI Approved :: MIT License
Classifier: Operating System :: Microsoft :: Windows
Classifier: Operating System :: POSIX :: Linux
Classifier: Programming Language :: Python
Classifier: Programming Language :: Python :: 3.8
Classifier: Programming Language :: Python :: 3.9
Classifier: Programming Language :: Python :: 3.10
Classifier: Programming Language :: Python :: 3.11
Classifier: Programming Language :: Python :: 3.12
Classifier: Programming Language :: Python :: 3.13
Classifier: Programming Language :: Python :: Implementation :: CPython
Classifier: Typing :: Typed
Requires-Python: >=3.8
